		
.class WordProcessor
.super java/lang/Object
		
.method public <init>()V
		.limit stack 128
		.limit locals 128
		aload_0
		invokespecial java/lang/Object/<init>()V
		return
.end method
		
.method map(LList;)LList;
		.limit stack 128
		.limit locals 128
		new java/lang/String
		dup
		ldc ""
		invokespecial java/lang/String/<init>(Ljava/lang/String;)V
		astore_2
		new java/lang/Integer
		dup
		iconst_0
		invokespecial java/lang/Integer/<init>(I)V
		astore_3
		new java/lang/Boolean
		dup
		iconst_0
		invokespecial java/lang/Boolean/<init>(Z)V
		astore_4
		new List
		dup 
		new java/util/ArrayList
		dup 
		invokespecial java/util/ArrayList/<init>()V
		dup
		new List
		dup 
		new java/util/ArrayList
		dup 
		invokespecial java/util/ArrayList/<init>()V
		dup
		new java/lang/String
		dup
		ldc ""
		invokespecial java/lang/String/<init>(Ljava/lang/String;)V
		invokevirtual java/util/ArrayList/add(Ljava/lang/Object;)V
		dup
		new java/lang/Integer
		dup
		iconst_0
		invokespecial java/lang/Integer/<init>(I)V
		invokevirtual java/util/ArrayList/add(Ljava/lang/Object;)V
		invokespecial List/<init>(Ljava/util/ArrayList;)V
		invokevirtual java/util/ArrayList/add(Ljava/lang/Object;)V
		dup
		new List
		dup 
		new java/util/ArrayList
		dup 
		invokespecial java/util/ArrayList/<init>()V
		dup
		new java/lang/String
		dup
		ldc ""
		invokespecial java/lang/String/<init>(Ljava/lang/String;)V
		invokevirtual java/util/ArrayList/add(Ljava/lang/Object;)V
		dup
		new java/lang/Integer
		dup
		iconst_0
		invokespecial java/lang/Integer/<init>(I)V
		invokevirtual java/util/ArrayList/add(Ljava/lang/Object;)V
		invokespecial List/<init>(Ljava/util/ArrayList;)V
		invokevirtual java/util/ArrayList/add(Ljava/lang/Object;)V
		dup
		new List
		dup 
		new java/util/ArrayList
		dup 
		invokespecial java/util/ArrayList/<init>()V
		dup
		new java/lang/String
		dup
		ldc ""
		invokespecial java/lang/String/<init>(Ljava/lang/String;)V
		invokevirtual java/util/ArrayList/add(Ljava/lang/Object;)V
		dup
		new java/lang/Integer
		dup
		iconst_0
		invokespecial java/lang/Integer/<init>(I)V
		invokevirtual java/util/ArrayList/add(Ljava/lang/Object;)V
		invokespecial List/<init>(Ljava/util/ArrayList;)V
		invokevirtual java/util/ArrayList/add(Ljava/lang/Object;)V
		dup
		new List
		dup 
		new java/util/ArrayList
		dup 
		invokespecial java/util/ArrayList/<init>()V
		dup
		new java/lang/String
		dup
		ldc ""
		invokespecial java/lang/String/<init>(Ljava/lang/String;)V
		invokevirtual java/util/ArrayList/add(Ljava/lang/Object;)V
		dup
		new java/lang/Integer
		dup
		iconst_0
		invokespecial java/lang/Integer/<init>(I)V
		invokevirtual java/util/ArrayList/add(Ljava/lang/Object;)V
		invokespecial List/<init>(Ljava/util/ArrayList;)V
		invokevirtual java/util/ArrayList/add(Ljava/lang/Object;)V
		dup
		new List
		dup 
		new java/util/ArrayList
		dup 
		invokespecial java/util/ArrayList/<init>()V
		dup
		new java/lang/String
		dup
		ldc ""
		invokespecial java/lang/String/<init>(Ljava/lang/String;)V
		invokevirtual java/util/ArrayList/add(Ljava/lang/Object;)V
		dup
		new java/lang/Integer
		dup
		iconst_0
		invokespecial java/lang/Integer/<init>(I)V
		invokevirtual java/util/ArrayList/add(Ljava/lang/Object;)V
		invokespecial List/<init>(Ljava/util/ArrayList;)V
		invokevirtual java/util/ArrayList/add(Ljava/lang/Object;)V
		dup
		new List
		dup 
		new java/util/ArrayList
		dup 
		invokespecial java/util/ArrayList/<init>()V
		dup
		new java/lang/String
		dup
		ldc ""
		invokespecial java/lang/String/<init>(Ljava/lang/String;)V
		invokevirtual java/util/ArrayList/add(Ljava/lang/Object;)V
		dup
		new java/lang/Integer
		dup
		iconst_0
		invokespecial java/lang/Integer/<init>(I)V
		invokevirtual java/util/ArrayList/add(Ljava/lang/Object;)V
		invokespecial List/<init>(Ljava/util/ArrayList;)V
		invokevirtual java/util/ArrayList/add(Ljava/lang/Object;)V
		dup
		new List
		dup 
		new java/util/ArrayList
		dup 
		invokespecial java/util/ArrayList/<init>()V
		dup
		new java/lang/String
		dup
		ldc ""
		invokespecial java/lang/String/<init>(Ljava/lang/String;)V
		invokevirtual java/util/ArrayList/add(Ljava/lang/Object;)V
		dup
		new java/lang/Integer
		dup
		iconst_0
		invokespecial java/lang/Integer/<init>(I)V
		invokevirtual java/util/ArrayList/add(Ljava/lang/Object;)V
		invokespecial List/<init>(Ljava/util/ArrayList;)V
		invokevirtual java/util/ArrayList/add(Ljava/lang/Object;)V
		dup
		new List
		dup 
		new java/util/ArrayList
		dup 
		invokespecial java/util/ArrayList/<init>()V
		dup
		new java/lang/String
		dup
		ldc ""
		invokespecial java/lang/String/<init>(Ljava/lang/String;)V
		invokevirtual java/util/ArrayList/add(Ljava/lang/Object;)V
		dup
		new java/lang/Integer
		dup
		iconst_0
		invokespecial java/lang/Integer/<init>(I)V
		invokevirtual java/util/ArrayList/add(Ljava/lang/Object;)V
		invokespecial List/<init>(Ljava/util/ArrayList;)V
		invokevirtual java/util/ArrayList/add(Ljava/lang/Object;)V
		dup
		new List
		dup 
		new java/util/ArrayList
		dup 
		invokespecial java/util/ArrayList/<init>()V
		dup
		new java/lang/String
		dup
		ldc ""
		invokespecial java/lang/String/<init>(Ljava/lang/String;)V
		invokevirtual java/util/ArrayList/add(Ljava/lang/Object;)V
		dup
		new java/lang/Integer
		dup
		iconst_0
		invokespecial java/lang/Integer/<init>(I)V
		invokevirtual java/util/ArrayList/add(Ljava/lang/Object;)V
		invokespecial List/<init>(Ljava/util/ArrayList;)V
		invokevirtual java/util/ArrayList/add(Ljava/lang/Object;)V
		dup
		new List
		dup 
		new java/util/ArrayList
		dup 
		invokespecial java/util/ArrayList/<init>()V
		dup
		new java/lang/String
		dup
		ldc ""
		invokespecial java/lang/String/<init>(Ljava/lang/String;)V
		invokevirtual java/util/ArrayList/add(Ljava/lang/Object;)V
		dup
		new java/lang/Integer
		dup
		iconst_0
		invokespecial java/lang/Integer/<init>(I)V
		invokevirtual java/util/ArrayList/add(Ljava/lang/Object;)V
		invokespecial List/<init>(Ljava/util/ArrayList;)V
		invokevirtual java/util/ArrayList/add(Ljava/lang/Object;)V
		dup
		new List
		dup 
		new java/util/ArrayList
		dup 
		invokespecial java/util/ArrayList/<init>()V
		dup
		new java/lang/String
		dup
		ldc ""
		invokespecial java/lang/String/<init>(Ljava/lang/String;)V
		invokevirtual java/util/ArrayList/add(Ljava/lang/Object;)V
		dup
		new java/lang/Integer
		dup
		iconst_0
		invokespecial java/lang/Integer/<init>(I)V
		invokevirtual java/util/ArrayList/add(Ljava/lang/Object;)V
		invokespecial List/<init>(Ljava/util/ArrayList;)V
		invokevirtual java/util/ArrayList/add(Ljava/lang/Object;)V
		dup
		new List
		dup 
		new java/util/ArrayList
		dup 
		invokespecial java/util/ArrayList/<init>()V
		dup
		new java/lang/String
		dup
		ldc ""
		invokespecial java/lang/String/<init>(Ljava/lang/String;)V
		invokevirtual java/util/ArrayList/add(Ljava/lang/Object;)V
		dup
		new java/lang/Integer
		dup
		iconst_0
		invokespecial java/lang/Integer/<init>(I)V
		invokevirtual java/util/ArrayList/add(Ljava/lang/Object;)V
		invokespecial List/<init>(Ljava/util/ArrayList;)V
		invokevirtual java/util/ArrayList/add(Ljava/lang/Object;)V
		dup
		new List
		dup 
		new java/util/ArrayList
		dup 
		invokespecial java/util/ArrayList/<init>()V
		dup
		new java/lang/String
		dup
		ldc ""
		invokespecial java/lang/String/<init>(Ljava/lang/String;)V
		invokevirtual java/util/ArrayList/add(Ljava/lang/Object;)V
		dup
		new java/lang/Integer
		dup
		iconst_0
		invokespecial java/lang/Integer/<init>(I)V
		invokevirtual java/util/ArrayList/add(Ljava/lang/Object;)V
		invokespecial List/<init>(Ljava/util/ArrayList;)V
		invokevirtual java/util/ArrayList/add(Ljava/lang/Object;)V
		dup
		new List
		dup 
		new java/util/ArrayList
		dup 
		invokespecial java/util/ArrayList/<init>()V
		dup
		new java/lang/String
		dup
		ldc ""
		invokespecial java/lang/String/<init>(Ljava/lang/String;)V
		invokevirtual java/util/ArrayList/add(Ljava/lang/Object;)V
		dup
		new java/lang/Integer
		dup
		iconst_0
		invokespecial java/lang/Integer/<init>(I)V
		invokevirtual java/util/ArrayList/add(Ljava/lang/Object;)V
		invokespecial List/<init>(Ljava/util/ArrayList;)V
		invokevirtual java/util/ArrayList/add(Ljava/lang/Object;)V
		dup
		new List
		dup 
		new java/util/ArrayList
		dup 
		invokespecial java/util/ArrayList/<init>()V
		dup
		new java/lang/String
		dup
		ldc ""
		invokespecial java/lang/String/<init>(Ljava/lang/String;)V
		invokevirtual java/util/ArrayList/add(Ljava/lang/Object;)V
		dup
		new java/lang/Integer
		dup
		iconst_0
		invokespecial java/lang/Integer/<init>(I)V
		invokevirtual java/util/ArrayList/add(Ljava/lang/Object;)V
		invokespecial List/<init>(Ljava/util/ArrayList;)V
		invokevirtual java/util/ArrayList/add(Ljava/lang/Object;)V
		dup
		new List
		dup 
		new java/util/ArrayList
		dup 
		invokespecial java/util/ArrayList/<init>()V
		dup
		new java/lang/String
		dup
		ldc ""
		invokespecial java/lang/String/<init>(Ljava/lang/String;)V
		invokevirtual java/util/ArrayList/add(Ljava/lang/Object;)V
		dup
		new java/lang/Integer
		dup
		iconst_0
		invokespecial java/lang/Integer/<init>(I)V
		invokevirtual java/util/ArrayList/add(Ljava/lang/Object;)V
		invokespecial List/<init>(Ljava/util/ArrayList;)V
		invokevirtual java/util/ArrayList/add(Ljava/lang/Object;)V
		dup
		new List
		dup 
		new java/util/ArrayList
		dup 
		invokespecial java/util/ArrayList/<init>()V
		dup
		new java/lang/String
		dup
		ldc ""
		invokespecial java/lang/String/<init>(Ljava/lang/String;)V
		invokevirtual java/util/ArrayList/add(Ljava/lang/Object;)V
		dup
		new java/lang/Integer
		dup
		iconst_0
		invokespecial java/lang/Integer/<init>(I)V
		invokevirtual java/util/ArrayList/add(Ljava/lang/Object;)V
		invokespecial List/<init>(Ljava/util/ArrayList;)V
		invokevirtual java/util/ArrayList/add(Ljava/lang/Object;)V
		dup
		new List
		dup 
		new java/util/ArrayList
		dup 
		invokespecial java/util/ArrayList/<init>()V
		dup
		new java/lang/String
		dup
		ldc ""
		invokespecial java/lang/String/<init>(Ljava/lang/String;)V
		invokevirtual java/util/ArrayList/add(Ljava/lang/Object;)V
		dup
		new java/lang/Integer
		dup
		iconst_0
		invokespecial java/lang/Integer/<init>(I)V
		invokevirtual java/util/ArrayList/add(Ljava/lang/Object;)V
		invokespecial List/<init>(Ljava/util/ArrayList;)V
		invokevirtual java/util/ArrayList/add(Ljava/lang/Object;)V
		dup
		new List
		dup 
		new java/util/ArrayList
		dup 
		invokespecial java/util/ArrayList/<init>()V
		dup
		new java/lang/String
		dup
		ldc ""
		invokespecial java/lang/String/<init>(Ljava/lang/String;)V
		invokevirtual java/util/ArrayList/add(Ljava/lang/Object;)V
		dup
		new java/lang/Integer
		dup
		iconst_0
		invokespecial java/lang/Integer/<init>(I)V
		invokevirtual java/util/ArrayList/add(Ljava/lang/Object;)V
		invokespecial List/<init>(Ljava/util/ArrayList;)V
		invokevirtual java/util/ArrayList/add(Ljava/lang/Object;)V
		dup
		new List
		dup 
		new java/util/ArrayList
		dup 
		invokespecial java/util/ArrayList/<init>()V
		dup
		new java/lang/String
		dup
		ldc ""
		invokespecial java/lang/String/<init>(Ljava/lang/String;)V
		invokevirtual java/util/ArrayList/add(Ljava/lang/Object;)V
		dup
		new java/lang/Integer
		dup
		iconst_0
		invokespecial java/lang/Integer/<init>(I)V
		invokevirtual java/util/ArrayList/add(Ljava/lang/Object;)V
		invokespecial List/<init>(Ljava/util/ArrayList;)V
		invokevirtual java/util/ArrayList/add(Ljava/lang/Object;)V
		dup
		new List
		dup 
		new java/util/ArrayList
		dup 
		invokespecial java/util/ArrayList/<init>()V
		dup
		new java/lang/String
		dup
		ldc ""
		invokespecial java/lang/String/<init>(Ljava/lang/String;)V
		invokevirtual java/util/ArrayList/add(Ljava/lang/Object;)V
		dup
		new java/lang/Integer
		dup
		iconst_0
		invokespecial java/lang/Integer/<init>(I)V
		invokevirtual java/util/ArrayList/add(Ljava/lang/Object;)V
		invokespecial List/<init>(Ljava/util/ArrayList;)V
		invokevirtual java/util/ArrayList/add(Ljava/lang/Object;)V
		dup
		new List
		dup 
		new java/util/ArrayList
		dup 
		invokespecial java/util/ArrayList/<init>()V
		dup
		new java/lang/String
		dup
		ldc ""
		invokespecial java/lang/String/<init>(Ljava/lang/String;)V
		invokevirtual java/util/ArrayList/add(Ljava/lang/Object;)V
		dup
		new java/lang/Integer
		dup
		iconst_0
		invokespecial java/lang/Integer/<init>(I)V
		invokevirtual java/util/ArrayList/add(Ljava/lang/Object;)V
		invokespecial List/<init>(Ljava/util/ArrayList;)V
		invokevirtual java/util/ArrayList/add(Ljava/lang/Object;)V
		dup
		new List
		dup 
		new java/util/ArrayList
		dup 
		invokespecial java/util/ArrayList/<init>()V
		dup
		new java/lang/String
		dup
		ldc ""
		invokespecial java/lang/String/<init>(Ljava/lang/String;)V
		invokevirtual java/util/ArrayList/add(Ljava/lang/Object;)V
		dup
		new java/lang/Integer
		dup
		iconst_0
		invokespecial java/lang/Integer/<init>(I)V
		invokevirtual java/util/ArrayList/add(Ljava/lang/Object;)V
		invokespecial List/<init>(Ljava/util/ArrayList;)V
		invokevirtual java/util/ArrayList/add(Ljava/lang/Object;)V
		dup
		new List
		dup 
		new java/util/ArrayList
		dup 
		invokespecial java/util/ArrayList/<init>()V
		dup
		new java/lang/String
		dup
		ldc ""
		invokespecial java/lang/String/<init>(Ljava/lang/String;)V
		invokevirtual java/util/ArrayList/add(Ljava/lang/Object;)V
		dup
		new java/lang/Integer
		dup
		iconst_0
		invokespecial java/lang/Integer/<init>(I)V
		invokevirtual java/util/ArrayList/add(Ljava/lang/Object;)V
		invokespecial List/<init>(Ljava/util/ArrayList;)V
		invokevirtual java/util/ArrayList/add(Ljava/lang/Object;)V
		dup
		new List
		dup 
		new java/util/ArrayList
		dup 
		invokespecial java/util/ArrayList/<init>()V
		dup
		new java/lang/String
		dup
		ldc ""
		invokespecial java/lang/String/<init>(Ljava/lang/String;)V
		invokevirtual java/util/ArrayList/add(Ljava/lang/Object;)V
		dup
		new java/lang/Integer
		dup
		iconst_0
		invokespecial java/lang/Integer/<init>(I)V
		invokevirtual java/util/ArrayList/add(Ljava/lang/Object;)V
		invokespecial List/<init>(Ljava/util/ArrayList;)V
		invokevirtual java/util/ArrayList/add(Ljava/lang/Object;)V
		dup
		new List
		dup 
		new java/util/ArrayList
		dup 
		invokespecial java/util/ArrayList/<init>()V
		dup
		new java/lang/String
		dup
		ldc ""
		invokespecial java/lang/String/<init>(Ljava/lang/String;)V
		invokevirtual java/util/ArrayList/add(Ljava/lang/Object;)V
		dup
		new java/lang/Integer
		dup
		iconst_0
		invokespecial java/lang/Integer/<init>(I)V
		invokevirtual java/util/ArrayList/add(Ljava/lang/Object;)V
		invokespecial List/<init>(Ljava/util/ArrayList;)V
		invokevirtual java/util/ArrayList/add(Ljava/lang/Object;)V
		dup
		new List
		dup 
		new java/util/ArrayList
		dup 
		invokespecial java/util/ArrayList/<init>()V
		dup
		new java/lang/String
		dup
		ldc ""
		invokespecial java/lang/String/<init>(Ljava/lang/String;)V
		invokevirtual java/util/ArrayList/add(Ljava/lang/Object;)V
		dup
		new java/lang/Integer
		dup
		iconst_0
		invokespecial java/lang/Integer/<init>(I)V
		invokevirtual java/util/ArrayList/add(Ljava/lang/Object;)V
		invokespecial List/<init>(Ljava/util/ArrayList;)V
		invokevirtual java/util/ArrayList/add(Ljava/lang/Object;)V
		dup
		new List
		dup 
		new java/util/ArrayList
		dup 
		invokespecial java/util/ArrayList/<init>()V
		dup
		new java/lang/String
		dup
		ldc ""
		invokespecial java/lang/String/<init>(Ljava/lang/String;)V
		invokevirtual java/util/ArrayList/add(Ljava/lang/Object;)V
		dup
		new java/lang/Integer
		dup
		iconst_0
		invokespecial java/lang/Integer/<init>(I)V
		invokevirtual java/util/ArrayList/add(Ljava/lang/Object;)V
		invokespecial List/<init>(Ljava/util/ArrayList;)V
		invokevirtual java/util/ArrayList/add(Ljava/lang/Object;)V
		dup
		new List
		dup 
		new java/util/ArrayList
		dup 
		invokespecial java/util/ArrayList/<init>()V
		dup
		new java/lang/String
		dup
		ldc ""
		invokespecial java/lang/String/<init>(Ljava/lang/String;)V
		invokevirtual java/util/ArrayList/add(Ljava/lang/Object;)V
		dup
		new java/lang/Integer
		dup
		iconst_0
		invokespecial java/lang/Integer/<init>(I)V
		invokevirtual java/util/ArrayList/add(Ljava/lang/Object;)V
		invokespecial List/<init>(Ljava/util/ArrayList;)V
		invokevirtual java/util/ArrayList/add(Ljava/lang/Object;)V
		dup
		new List
		dup 
		new java/util/ArrayList
		dup 
		invokespecial java/util/ArrayList/<init>()V
		dup
		new java/lang/String
		dup
		ldc ""
		invokespecial java/lang/String/<init>(Ljava/lang/String;)V
		invokevirtual java/util/ArrayList/add(Ljava/lang/Object;)V
		dup
		new java/lang/Integer
		dup
		iconst_0
		invokespecial java/lang/Integer/<init>(I)V
		invokevirtual java/util/ArrayList/add(Ljava/lang/Object;)V
		invokespecial List/<init>(Ljava/util/ArrayList;)V
		invokevirtual java/util/ArrayList/add(Ljava/lang/Object;)V
		dup
		new List
		dup 
		new java/util/ArrayList
		dup 
		invokespecial java/util/ArrayList/<init>()V
		dup
		new java/lang/String
		dup
		ldc ""
		invokespecial java/lang/String/<init>(Ljava/lang/String;)V
		invokevirtual java/util/ArrayList/add(Ljava/lang/Object;)V
		dup
		new java/lang/Integer
		dup
		iconst_0
		invokespecial java/lang/Integer/<init>(I)V
		invokevirtual java/util/ArrayList/add(Ljava/lang/Object;)V
		invokespecial List/<init>(Ljava/util/ArrayList;)V
		invokevirtual java/util/ArrayList/add(Ljava/lang/Object;)V
		dup
		new List
		dup 
		new java/util/ArrayList
		dup 
		invokespecial java/util/ArrayList/<init>()V
		dup
		new java/lang/String
		dup
		ldc ""
		invokespecial java/lang/String/<init>(Ljava/lang/String;)V
		invokevirtual java/util/ArrayList/add(Ljava/lang/Object;)V
		dup
		new java/lang/Integer
		dup
		iconst_0
		invokespecial java/lang/Integer/<init>(I)V
		invokevirtual java/util/ArrayList/add(Ljava/lang/Object;)V
		invokespecial List/<init>(Ljava/util/ArrayList;)V
		invokevirtual java/util/ArrayList/add(Ljava/lang/Object;)V
		dup
		new List
		dup 
		new java/util/ArrayList
		dup 
		invokespecial java/util/ArrayList/<init>()V
		dup
		new java/lang/String
		dup
		ldc ""
		invokespecial java/lang/String/<init>(Ljava/lang/String;)V
		invokevirtual java/util/ArrayList/add(Ljava/lang/Object;)V
		dup
		new java/lang/Integer
		dup
		iconst_0
		invokespecial java/lang/Integer/<init>(I)V
		invokevirtual java/util/ArrayList/add(Ljava/lang/Object;)V
		invokespecial List/<init>(Ljava/util/ArrayList;)V
		invokevirtual java/util/ArrayList/add(Ljava/lang/Object;)V
		dup
		new List
		dup 
		new java/util/ArrayList
		dup 
		invokespecial java/util/ArrayList/<init>()V
		dup
		new java/lang/String
		dup
		ldc ""
		invokespecial java/lang/String/<init>(Ljava/lang/String;)V
		invokevirtual java/util/ArrayList/add(Ljava/lang/Object;)V
		dup
		new java/lang/Integer
		dup
		iconst_0
		invokespecial java/lang/Integer/<init>(I)V
		invokevirtual java/util/ArrayList/add(Ljava/lang/Object;)V
		invokespecial List/<init>(Ljava/util/ArrayList;)V
		invokevirtual java/util/ArrayList/add(Ljava/lang/Object;)V
		dup
		new List
		dup 
		new java/util/ArrayList
		dup 
		invokespecial java/util/ArrayList/<init>()V
		dup
		new java/lang/String
		dup
		ldc ""
		invokespecial java/lang/String/<init>(Ljava/lang/String;)V
		invokevirtual java/util/ArrayList/add(Ljava/lang/Object;)V
		dup
		new java/lang/Integer
		dup
		iconst_0
		invokespecial java/lang/Integer/<init>(I)V
		invokevirtual java/util/ArrayList/add(Ljava/lang/Object;)V
		invokespecial List/<init>(Ljava/util/ArrayList;)V
		invokevirtual java/util/ArrayList/add(Ljava/lang/Object;)V
		dup
		new List
		dup 
		new java/util/ArrayList
		dup 
		invokespecial java/util/ArrayList/<init>()V
		dup
		new java/lang/String
		dup
		ldc ""
		invokespecial java/lang/String/<init>(Ljava/lang/String;)V
		invokevirtual java/util/ArrayList/add(Ljava/lang/Object;)V
		dup
		new java/lang/Integer
		dup
		iconst_0
		invokespecial java/lang/Integer/<init>(I)V
		invokevirtual java/util/ArrayList/add(Ljava/lang/Object;)V
		invokespecial List/<init>(Ljava/util/ArrayList;)V
		invokevirtual java/util/ArrayList/add(Ljava/lang/Object;)V
		dup
		new List
		dup 
		new java/util/ArrayList
		dup 
		invokespecial java/util/ArrayList/<init>()V
		dup
		new java/lang/String
		dup
		ldc ""
		invokespecial java/lang/String/<init>(Ljava/lang/String;)V
		invokevirtual java/util/ArrayList/add(Ljava/lang/Object;)V
		dup
		new java/lang/Integer
		dup
		iconst_0
		invokespecial java/lang/Integer/<init>(I)V
		invokevirtual java/util/ArrayList/add(Ljava/lang/Object;)V
		invokespecial List/<init>(Ljava/util/ArrayList;)V
		invokevirtual java/util/ArrayList/add(Ljava/lang/Object;)V
		dup
		new List
		dup 
		new java/util/ArrayList
		dup 
		invokespecial java/util/ArrayList/<init>()V
		dup
		new java/lang/String
		dup
		ldc ""
		invokespecial java/lang/String/<init>(Ljava/lang/String;)V
		invokevirtual java/util/ArrayList/add(Ljava/lang/Object;)V
		dup
		new java/lang/Integer
		dup
		iconst_0
		invokespecial java/lang/Integer/<init>(I)V
		invokevirtual java/util/ArrayList/add(Ljava/lang/Object;)V
		invokespecial List/<init>(Ljava/util/ArrayList;)V
		invokevirtual java/util/ArrayList/add(Ljava/lang/Object;)V
		dup
		new List
		dup 
		new java/util/ArrayList
		dup 
		invokespecial java/util/ArrayList/<init>()V
		dup
		new java/lang/String
		dup
		ldc ""
		invokespecial java/lang/String/<init>(Ljava/lang/String;)V
		invokevirtual java/util/ArrayList/add(Ljava/lang/Object;)V
		dup
		new java/lang/Integer
		dup
		iconst_0
		invokespecial java/lang/Integer/<init>(I)V
		invokevirtual java/util/ArrayList/add(Ljava/lang/Object;)V
		invokespecial List/<init>(Ljava/util/ArrayList;)V
		invokevirtual java/util/ArrayList/add(Ljava/lang/Object;)V
		dup
		new List
		dup 
		new java/util/ArrayList
		dup 
		invokespecial java/util/ArrayList/<init>()V
		dup
		new java/lang/String
		dup
		ldc ""
		invokespecial java/lang/String/<init>(Ljava/lang/String;)V
		invokevirtual java/util/ArrayList/add(Ljava/lang/Object;)V
		dup
		new java/lang/Integer
		dup
		iconst_0
		invokespecial java/lang/Integer/<init>(I)V
		invokevirtual java/util/ArrayList/add(Ljava/lang/Object;)V
		invokespecial List/<init>(Ljava/util/ArrayList;)V
		invokevirtual java/util/ArrayList/add(Ljava/lang/Object;)V
		dup
		new List
		dup 
		new java/util/ArrayList
		dup 
		invokespecial java/util/ArrayList/<init>()V
		dup
		new java/lang/String
		dup
		ldc ""
		invokespecial java/lang/String/<init>(Ljava/lang/String;)V
		invokevirtual java/util/ArrayList/add(Ljava/lang/Object;)V
		dup
		new java/lang/Integer
		dup
		iconst_0
		invokespecial java/lang/Integer/<init>(I)V
		invokevirtual java/util/ArrayList/add(Ljava/lang/Object;)V
		invokespecial List/<init>(Ljava/util/ArrayList;)V
		invokevirtual java/util/ArrayList/add(Ljava/lang/Object;)V
		dup
		new List
		dup 
		new java/util/ArrayList
		dup 
		invokespecial java/util/ArrayList/<init>()V
		dup
		new java/lang/String
		dup
		ldc ""
		invokespecial java/lang/String/<init>(Ljava/lang/String;)V
		invokevirtual java/util/ArrayList/add(Ljava/lang/Object;)V
		dup
		new java/lang/Integer
		dup
		iconst_0
		invokespecial java/lang/Integer/<init>(I)V
		invokevirtual java/util/ArrayList/add(Ljava/lang/Object;)V
		invokespecial List/<init>(Ljava/util/ArrayList;)V
		invokevirtual java/util/ArrayList/add(Ljava/lang/Object;)V
		dup
		new List
		dup 
		new java/util/ArrayList
		dup 
		invokespecial java/util/ArrayList/<init>()V
		dup
		new java/lang/String
		dup
		ldc ""
		invokespecial java/lang/String/<init>(Ljava/lang/String;)V
		invokevirtual java/util/ArrayList/add(Ljava/lang/Object;)V
		dup
		new java/lang/Integer
		dup
		iconst_0
		invokespecial java/lang/Integer/<init>(I)V
		invokevirtual java/util/ArrayList/add(Ljava/lang/Object;)V
		invokespecial List/<init>(Ljava/util/ArrayList;)V
		invokevirtual java/util/ArrayList/add(Ljava/lang/Object;)V
		dup
		new List
		dup 
		new java/util/ArrayList
		dup 
		invokespecial java/util/ArrayList/<init>()V
		dup
		new java/lang/String
		dup
		ldc ""
		invokespecial java/lang/String/<init>(Ljava/lang/String;)V
		invokevirtual java/util/ArrayList/add(Ljava/lang/Object;)V
		dup
		new java/lang/Integer
		dup
		iconst_0
		invokespecial java/lang/Integer/<init>(I)V
		invokevirtual java/util/ArrayList/add(Ljava/lang/Object;)V
		invokespecial List/<init>(Ljava/util/ArrayList;)V
		invokevirtual java/util/ArrayList/add(Ljava/lang/Object;)V
		dup
		new List
		dup 
		new java/util/ArrayList
		dup 
		invokespecial java/util/ArrayList/<init>()V
		dup
		new java/lang/String
		dup
		ldc ""
		invokespecial java/lang/String/<init>(Ljava/lang/String;)V
		invokevirtual java/util/ArrayList/add(Ljava/lang/Object;)V
		dup
		new java/lang/Integer
		dup
		iconst_0
		invokespecial java/lang/Integer/<init>(I)V
		invokevirtual java/util/ArrayList/add(Ljava/lang/Object;)V
		invokespecial List/<init>(Ljava/util/ArrayList;)V
		invokevirtual java/util/ArrayList/add(Ljava/lang/Object;)V
		dup
		new List
		dup 
		new java/util/ArrayList
		dup 
		invokespecial java/util/ArrayList/<init>()V
		dup
		new java/lang/String
		dup
		ldc ""
		invokespecial java/lang/String/<init>(Ljava/lang/String;)V
		invokevirtual java/util/ArrayList/add(Ljava/lang/Object;)V
		dup
		new java/lang/Integer
		dup
		iconst_0
		invokespecial java/lang/Integer/<init>(I)V
		invokevirtual java/util/ArrayList/add(Ljava/lang/Object;)V
		invokespecial List/<init>(Ljava/util/ArrayList;)V
		invokevirtual java/util/ArrayList/add(Ljava/lang/Object;)V
		dup
		new List
		dup 
		new java/util/ArrayList
		dup 
		invokespecial java/util/ArrayList/<init>()V
		dup
		new java/lang/String
		dup
		ldc ""
		invokespecial java/lang/String/<init>(Ljava/lang/String;)V
		invokevirtual java/util/ArrayList/add(Ljava/lang/Object;)V
		dup
		new java/lang/Integer
		dup
		iconst_0
		invokespecial java/lang/Integer/<init>(I)V
		invokevirtual java/util/ArrayList/add(Ljava/lang/Object;)V
		invokespecial List/<init>(Ljava/util/ArrayList;)V
		invokevirtual java/util/ArrayList/add(Ljava/lang/Object;)V
		dup
		new List
		dup 
		new java/util/ArrayList
		dup 
		invokespecial java/util/ArrayList/<init>()V
		dup
		new java/lang/String
		dup
		ldc ""
		invokespecial java/lang/String/<init>(Ljava/lang/String;)V
		invokevirtual java/util/ArrayList/add(Ljava/lang/Object;)V
		dup
		new java/lang/Integer
		dup
		iconst_0
		invokespecial java/lang/Integer/<init>(I)V
		invokevirtual java/util/ArrayList/add(Ljava/lang/Object;)V
		invokespecial List/<init>(Ljava/util/ArrayList;)V
		invokevirtual java/util/ArrayList/add(Ljava/lang/Object;)V
		dup
		new List
		dup 
		new java/util/ArrayList
		dup 
		invokespecial java/util/ArrayList/<init>()V
		dup
		new java/lang/String
		dup
		ldc ""
		invokespecial java/lang/String/<init>(Ljava/lang/String;)V
		invokevirtual java/util/ArrayList/add(Ljava/lang/Object;)V
		dup
		new java/lang/Integer
		dup
		iconst_0
		invokespecial java/lang/Integer/<init>(I)V
		invokevirtual java/util/ArrayList/add(Ljava/lang/Object;)V
		invokespecial List/<init>(Ljava/util/ArrayList;)V
		invokevirtual java/util/ArrayList/add(Ljava/lang/Object;)V
		dup
		new List
		dup 
		new java/util/ArrayList
		dup 
		invokespecial java/util/ArrayList/<init>()V
		dup
		new java/lang/String
		dup
		ldc ""
		invokespecial java/lang/String/<init>(Ljava/lang/String;)V
		invokevirtual java/util/ArrayList/add(Ljava/lang/Object;)V
		dup
		new java/lang/Integer
		dup
		iconst_0
		invokespecial java/lang/Integer/<init>(I)V
		invokevirtual java/util/ArrayList/add(Ljava/lang/Object;)V
		invokespecial List/<init>(Ljava/util/ArrayList;)V
		invokevirtual java/util/ArrayList/add(Ljava/lang/Object;)V
		dup
		new List
		dup 
		new java/util/ArrayList
		dup 
		invokespecial java/util/ArrayList/<init>()V
		dup
		new java/lang/String
		dup
		ldc ""
		invokespecial java/lang/String/<init>(Ljava/lang/String;)V
		invokevirtual java/util/ArrayList/add(Ljava/lang/Object;)V
		dup
		new java/lang/Integer
		dup
		iconst_0
		invokespecial java/lang/Integer/<init>(I)V
		invokevirtual java/util/ArrayList/add(Ljava/lang/Object;)V
		invokespecial List/<init>(Ljava/util/ArrayList;)V
		invokevirtual java/util/ArrayList/add(Ljava/lang/Object;)V
		dup
		new List
		dup 
		new java/util/ArrayList
		dup 
		invokespecial java/util/ArrayList/<init>()V
		dup
		new java/lang/String
		dup
		ldc ""
		invokespecial java/lang/String/<init>(Ljava/lang/String;)V
		invokevirtual java/util/ArrayList/add(Ljava/lang/Object;)V
		dup
		new java/lang/Integer
		dup
		iconst_0
		invokespecial java/lang/Integer/<init>(I)V
		invokevirtual java/util/ArrayList/add(Ljava/lang/Object;)V
		invokespecial List/<init>(Ljava/util/ArrayList;)V
		invokevirtual java/util/ArrayList/add(Ljava/lang/Object;)V
		dup
		new List
		dup 
		new java/util/ArrayList
		dup 
		invokespecial java/util/ArrayList/<init>()V
		dup
		new java/lang/String
		dup
		ldc ""
		invokespecial java/lang/String/<init>(Ljava/lang/String;)V
		invokevirtual java/util/ArrayList/add(Ljava/lang/Object;)V
		dup
		new java/lang/Integer
		dup
		iconst_0
		invokespecial java/lang/Integer/<init>(I)V
		invokevirtual java/util/ArrayList/add(Ljava/lang/Object;)V
		invokespecial List/<init>(Ljava/util/ArrayList;)V
		invokevirtual java/util/ArrayList/add(Ljava/lang/Object;)V
		dup
		new List
		dup 
		new java/util/ArrayList
		dup 
		invokespecial java/util/ArrayList/<init>()V
		dup
		new java/lang/String
		dup
		ldc ""
		invokespecial java/lang/String/<init>(Ljava/lang/String;)V
		invokevirtual java/util/ArrayList/add(Ljava/lang/Object;)V
		dup
		new java/lang/Integer
		dup
		iconst_0
		invokespecial java/lang/Integer/<init>(I)V
		invokevirtual java/util/ArrayList/add(Ljava/lang/Object;)V
		invokespecial List/<init>(Ljava/util/ArrayList;)V
		invokevirtual java/util/ArrayList/add(Ljava/lang/Object;)V
		dup
		new List
		dup 
		new java/util/ArrayList
		dup 
		invokespecial java/util/ArrayList/<init>()V
		dup
		new java/lang/String
		dup
		ldc ""
		invokespecial java/lang/String/<init>(Ljava/lang/String;)V
		invokevirtual java/util/ArrayList/add(Ljava/lang/Object;)V
		dup
		new java/lang/Integer
		dup
		iconst_0
		invokespecial java/lang/Integer/<init>(I)V
		invokevirtual java/util/ArrayList/add(Ljava/lang/Object;)V
		invokespecial List/<init>(Ljava/util/ArrayList;)V
		invokevirtual java/util/ArrayList/add(Ljava/lang/Object;)V
		dup
		new List
		dup 
		new java/util/ArrayList
		dup 
		invokespecial java/util/ArrayList/<init>()V
		dup
		new java/lang/String
		dup
		ldc ""
		invokespecial java/lang/String/<init>(Ljava/lang/String;)V
		invokevirtual java/util/ArrayList/add(Ljava/lang/Object;)V
		dup
		new java/lang/Integer
		dup
		iconst_0
		invokespecial java/lang/Integer/<init>(I)V
		invokevirtual java/util/ArrayList/add(Ljava/lang/Object;)V
		invokespecial List/<init>(Ljava/util/ArrayList;)V
		invokevirtual java/util/ArrayList/add(Ljava/lang/Object;)V
		dup
		new List
		dup 
		new java/util/ArrayList
		dup 
		invokespecial java/util/ArrayList/<init>()V
		dup
		new java/lang/String
		dup
		ldc ""
		invokespecial java/lang/String/<init>(Ljava/lang/String;)V
		invokevirtual java/util/ArrayList/add(Ljava/lang/Object;)V
		dup
		new java/lang/Integer
		dup
		iconst_0
		invokespecial java/lang/Integer/<init>(I)V
		invokevirtual java/util/ArrayList/add(Ljava/lang/Object;)V
		invokespecial List/<init>(Ljava/util/ArrayList;)V
		invokevirtual java/util/ArrayList/add(Ljava/lang/Object;)V
		dup
		new List
		dup 
		new java/util/ArrayList
		dup 
		invokespecial java/util/ArrayList/<init>()V
		dup
		new java/lang/String
		dup
		ldc ""
		invokespecial java/lang/String/<init>(Ljava/lang/String;)V
		invokevirtual java/util/ArrayList/add(Ljava/lang/Object;)V
		dup
		new java/lang/Integer
		dup
		iconst_0
		invokespecial java/lang/Integer/<init>(I)V
		invokevirtual java/util/ArrayList/add(Ljava/lang/Object;)V
		invokespecial List/<init>(Ljava/util/ArrayList;)V
		invokevirtual java/util/ArrayList/add(Ljava/lang/Object;)V
		dup
		new List
		dup 
		new java/util/ArrayList
		dup 
		invokespecial java/util/ArrayList/<init>()V
		dup
		new java/lang/String
		dup
		ldc ""
		invokespecial java/lang/String/<init>(Ljava/lang/String;)V
		invokevirtual java/util/ArrayList/add(Ljava/lang/Object;)V
		dup
		new java/lang/Integer
		dup
		iconst_0
		invokespecial java/lang/Integer/<init>(I)V
		invokevirtual java/util/ArrayList/add(Ljava/lang/Object;)V
		invokespecial List/<init>(Ljava/util/ArrayList;)V
		invokevirtual java/util/ArrayList/add(Ljava/lang/Object;)V
		dup
		new List
		dup 
		new java/util/ArrayList
		dup 
		invokespecial java/util/ArrayList/<init>()V
		dup
		new java/lang/String
		dup
		ldc ""
		invokespecial java/lang/String/<init>(Ljava/lang/String;)V
		invokevirtual java/util/ArrayList/add(Ljava/lang/Object;)V
		dup
		new java/lang/Integer
		dup
		iconst_0
		invokespecial java/lang/Integer/<init>(I)V
		invokevirtual java/util/ArrayList/add(Ljava/lang/Object;)V
		invokespecial List/<init>(Ljava/util/ArrayList;)V
		invokevirtual java/util/ArrayList/add(Ljava/lang/Object;)V
		dup
		new List
		dup 
		new java/util/ArrayList
		dup 
		invokespecial java/util/ArrayList/<init>()V
		dup
		new java/lang/String
		dup
		ldc ""
		invokespecial java/lang/String/<init>(Ljava/lang/String;)V
		invokevirtual java/util/ArrayList/add(Ljava/lang/Object;)V
		dup
		new java/lang/Integer
		dup
		iconst_0
		invokespecial java/lang/Integer/<init>(I)V
		invokevirtual java/util/ArrayList/add(Ljava/lang/Object;)V
		invokespecial List/<init>(Ljava/util/ArrayList;)V
		invokevirtual java/util/ArrayList/add(Ljava/lang/Object;)V
		dup
		new List
		dup 
		new java/util/ArrayList
		dup 
		invokespecial java/util/ArrayList/<init>()V
		dup
		new java/lang/String
		dup
		ldc ""
		invokespecial java/lang/String/<init>(Ljava/lang/String;)V
		invokevirtual java/util/ArrayList/add(Ljava/lang/Object;)V
		dup
		new java/lang/Integer
		dup
		iconst_0
		invokespecial java/lang/Integer/<init>(I)V
		invokevirtual java/util/ArrayList/add(Ljava/lang/Object;)V
		invokespecial List/<init>(Ljava/util/ArrayList;)V
		invokevirtual java/util/ArrayList/add(Ljava/lang/Object;)V
		dup
		new List
		dup 
		new java/util/ArrayList
		dup 
		invokespecial java/util/ArrayList/<init>()V
		dup
		new java/lang/String
		dup
		ldc ""
		invokespecial java/lang/String/<init>(Ljava/lang/String;)V
		invokevirtual java/util/ArrayList/add(Ljava/lang/Object;)V
		dup
		new java/lang/Integer
		dup
		iconst_0
		invokespecial java/lang/Integer/<init>(I)V
		invokevirtual java/util/ArrayList/add(Ljava/lang/Object;)V
		invokespecial List/<init>(Ljava/util/ArrayList;)V
		invokevirtual java/util/ArrayList/add(Ljava/lang/Object;)V
		dup
		new List
		dup 
		new java/util/ArrayList
		dup 
		invokespecial java/util/ArrayList/<init>()V
		dup
		new java/lang/String
		dup
		ldc ""
		invokespecial java/lang/String/<init>(Ljava/lang/String;)V
		invokevirtual java/util/ArrayList/add(Ljava/lang/Object;)V
		dup
		new java/lang/Integer
		dup
		iconst_0
		invokespecial java/lang/Integer/<init>(I)V
		invokevirtual java/util/ArrayList/add(Ljava/lang/Object;)V
		invokespecial List/<init>(Ljava/util/ArrayList;)V
		invokevirtual java/util/ArrayList/add(Ljava/lang/Object;)V
		dup
		new List
		dup 
		new java/util/ArrayList
		dup 
		invokespecial java/util/ArrayList/<init>()V
		dup
		new java/lang/String
		dup
		ldc ""
		invokespecial java/lang/String/<init>(Ljava/lang/String;)V
		invokevirtual java/util/ArrayList/add(Ljava/lang/Object;)V
		dup
		new java/lang/Integer
		dup
		iconst_0
		invokespecial java/lang/Integer/<init>(I)V
		invokevirtual java/util/ArrayList/add(Ljava/lang/Object;)V
		invokespecial List/<init>(Ljava/util/ArrayList;)V
		invokevirtual java/util/ArrayList/add(Ljava/lang/Object;)V
		dup
		new List
		dup 
		new java/util/ArrayList
		dup 
		invokespecial java/util/ArrayList/<init>()V
		dup
		new java/lang/String
		dup
		ldc ""
		invokespecial java/lang/String/<init>(Ljava/lang/String;)V
		invokevirtual java/util/ArrayList/add(Ljava/lang/Object;)V
		dup
		new java/lang/Integer
		dup
		iconst_0
		invokespecial java/lang/Integer/<init>(I)V
		invokevirtual java/util/ArrayList/add(Ljava/lang/Object;)V
		invokespecial List/<init>(Ljava/util/ArrayList;)V
		invokevirtual java/util/ArrayList/add(Ljava/lang/Object;)V
		dup
		new List
		dup 
		new java/util/ArrayList
		dup 
		invokespecial java/util/ArrayList/<init>()V
		dup
		new java/lang/String
		dup
		ldc ""
		invokespecial java/lang/String/<init>(Ljava/lang/String;)V
		invokevirtual java/util/ArrayList/add(Ljava/lang/Object;)V
		dup
		new java/lang/Integer
		dup
		iconst_0
		invokespecial java/lang/Integer/<init>(I)V
		invokevirtual java/util/ArrayList/add(Ljava/lang/Object;)V
		invokespecial List/<init>(Ljava/util/ArrayList;)V
		invokevirtual java/util/ArrayList/add(Ljava/lang/Object;)V
		dup
		new List
		dup 
		new java/util/ArrayList
		dup 
		invokespecial java/util/ArrayList/<init>()V
		dup
		new java/lang/String
		dup
		ldc ""
		invokespecial java/lang/String/<init>(Ljava/lang/String;)V
		invokevirtual java/util/ArrayList/add(Ljava/lang/Object;)V
		dup
		new java/lang/Integer
		dup
		iconst_0
		invokespecial java/lang/Integer/<init>(I)V
		invokevirtual java/util/ArrayList/add(Ljava/lang/Object;)V
		invokespecial List/<init>(Ljava/util/ArrayList;)V
		invokevirtual java/util/ArrayList/add(Ljava/lang/Object;)V
		dup
		new List
		dup 
		new java/util/ArrayList
		dup 
		invokespecial java/util/ArrayList/<init>()V
		dup
		new java/lang/String
		dup
		ldc ""
		invokespecial java/lang/String/<init>(Ljava/lang/String;)V
		invokevirtual java/util/ArrayList/add(Ljava/lang/Object;)V
		dup
		new java/lang/Integer
		dup
		iconst_0
		invokespecial java/lang/Integer/<init>(I)V
		invokevirtual java/util/ArrayList/add(Ljava/lang/Object;)V
		invokespecial List/<init>(Ljava/util/ArrayList;)V
		invokevirtual java/util/ArrayList/add(Ljava/lang/Object;)V
		dup
		new List
		dup 
		new java/util/ArrayList
		dup 
		invokespecial java/util/ArrayList/<init>()V
		dup
		new java/lang/String
		dup
		ldc ""
		invokespecial java/lang/String/<init>(Ljava/lang/String;)V
		invokevirtual java/util/ArrayList/add(Ljava/lang/Object;)V
		dup
		new java/lang/Integer
		dup
		iconst_0
		invokespecial java/lang/Integer/<init>(I)V
		invokevirtual java/util/ArrayList/add(Ljava/lang/Object;)V
		invokespecial List/<init>(Ljava/util/ArrayList;)V
		invokevirtual java/util/ArrayList/add(Ljava/lang/Object;)V
		dup
		new List
		dup 
		new java/util/ArrayList
		dup 
		invokespecial java/util/ArrayList/<init>()V
		dup
		new java/lang/String
		dup
		ldc ""
		invokespecial java/lang/String/<init>(Ljava/lang/String;)V
		invokevirtual java/util/ArrayList/add(Ljava/lang/Object;)V
		dup
		new java/lang/Integer
		dup
		iconst_0
		invokespecial java/lang/Integer/<init>(I)V
		invokevirtual java/util/ArrayList/add(Ljava/lang/Object;)V
		invokespecial List/<init>(Ljava/util/ArrayList;)V
		invokevirtual java/util/ArrayList/add(Ljava/lang/Object;)V
		dup
		new List
		dup 
		new java/util/ArrayList
		dup 
		invokespecial java/util/ArrayList/<init>()V
		dup
		new java/lang/String
		dup
		ldc ""
		invokespecial java/lang/String/<init>(Ljava/lang/String;)V
		invokevirtual java/util/ArrayList/add(Ljava/lang/Object;)V
		dup
		new java/lang/Integer
		dup
		iconst_0
		invokespecial java/lang/Integer/<init>(I)V
		invokevirtual java/util/ArrayList/add(Ljava/lang/Object;)V
		invokespecial List/<init>(Ljava/util/ArrayList;)V
		invokevirtual java/util/ArrayList/add(Ljava/lang/Object;)V
		dup
		new List
		dup 
		new java/util/ArrayList
		dup 
		invokespecial java/util/ArrayList/<init>()V
		dup
		new java/lang/String
		dup
		ldc ""
		invokespecial java/lang/String/<init>(Ljava/lang/String;)V
		invokevirtual java/util/ArrayList/add(Ljava/lang/Object;)V
		dup
		new java/lang/Integer
		dup
		iconst_0
		invokespecial java/lang/Integer/<init>(I)V
		invokevirtual java/util/ArrayList/add(Ljava/lang/Object;)V
		invokespecial List/<init>(Ljava/util/ArrayList;)V
		invokevirtual java/util/ArrayList/add(Ljava/lang/Object;)V
		dup
		new List
		dup 
		new java/util/ArrayList
		dup 
		invokespecial java/util/ArrayList/<init>()V
		dup
		new java/lang/String
		dup
		ldc ""
		invokespecial java/lang/String/<init>(Ljava/lang/String;)V
		invokevirtual java/util/ArrayList/add(Ljava/lang/Object;)V
		dup
		new java/lang/Integer
		dup
		iconst_0
		invokespecial java/lang/Integer/<init>(I)V
		invokevirtual java/util/ArrayList/add(Ljava/lang/Object;)V
		invokespecial List/<init>(Ljava/util/ArrayList;)V
		invokevirtual java/util/ArrayList/add(Ljava/lang/Object;)V
		dup
		new List
		dup 
		new java/util/ArrayList
		dup 
		invokespecial java/util/ArrayList/<init>()V
		dup
		new java/lang/String
		dup
		ldc ""
		invokespecial java/lang/String/<init>(Ljava/lang/String;)V
		invokevirtual java/util/ArrayList/add(Ljava/lang/Object;)V
		dup
		new java/lang/Integer
		dup
		iconst_0
		invokespecial java/lang/Integer/<init>(I)V
		invokevirtual java/util/ArrayList/add(Ljava/lang/Object;)V
		invokespecial List/<init>(Ljava/util/ArrayList;)V
		invokevirtual java/util/ArrayList/add(Ljava/lang/Object;)V
		dup
		new List
		dup 
		new java/util/ArrayList
		dup 
		invokespecial java/util/ArrayList/<init>()V
		dup
		new java/lang/String
		dup
		ldc ""
		invokespecial java/lang/String/<init>(Ljava/lang/String;)V
		invokevirtual java/util/ArrayList/add(Ljava/lang/Object;)V
		dup
		new java/lang/Integer
		dup
		iconst_0
		invokespecial java/lang/Integer/<init>(I)V
		invokevirtual java/util/ArrayList/add(Ljava/lang/Object;)V
		invokespecial List/<init>(Ljava/util/ArrayList;)V
		invokevirtual java/util/ArrayList/add(Ljava/lang/Object;)V
		dup
		new List
		dup 
		new java/util/ArrayList
		dup 
		invokespecial java/util/ArrayList/<init>()V
		dup
		new java/lang/String
		dup
		ldc ""
		invokespecial java/lang/String/<init>(Ljava/lang/String;)V
		invokevirtual java/util/ArrayList/add(Ljava/lang/Object;)V
		dup
		new java/lang/Integer
		dup
		iconst_0
		invokespecial java/lang/Integer/<init>(I)V
		invokevirtual java/util/ArrayList/add(Ljava/lang/Object;)V
		invokespecial List/<init>(Ljava/util/ArrayList;)V
		invokevirtual java/util/ArrayList/add(Ljava/lang/Object;)V
		dup
		new List
		dup 
		new java/util/ArrayList
		dup 
		invokespecial java/util/ArrayList/<init>()V
		dup
		new java/lang/String
		dup
		ldc ""
		invokespecial java/lang/String/<init>(Ljava/lang/String;)V
		invokevirtual java/util/ArrayList/add(Ljava/lang/Object;)V
		dup
		new java/lang/Integer
		dup
		iconst_0
		invokespecial java/lang/Integer/<init>(I)V
		invokevirtual java/util/ArrayList/add(Ljava/lang/Object;)V
		invokespecial List/<init>(Ljava/util/ArrayList;)V
		invokevirtual java/util/ArrayList/add(Ljava/lang/Object;)V
		dup
		new List
		dup 
		new java/util/ArrayList
		dup 
		invokespecial java/util/ArrayList/<init>()V
		dup
		new java/lang/String
		dup
		ldc ""
		invokespecial java/lang/String/<init>(Ljava/lang/String;)V
		invokevirtual java/util/ArrayList/add(Ljava/lang/Object;)V
		dup
		new java/lang/Integer
		dup
		iconst_0
		invokespecial java/lang/Integer/<init>(I)V
		invokevirtual java/util/ArrayList/add(Ljava/lang/Object;)V
		invokespecial List/<init>(Ljava/util/ArrayList;)V
		invokevirtual java/util/ArrayList/add(Ljava/lang/Object;)V
		dup
		new List
		dup 
		new java/util/ArrayList
		dup 
		invokespecial java/util/ArrayList/<init>()V
		dup
		new java/lang/String
		dup
		ldc ""
		invokespecial java/lang/String/<init>(Ljava/lang/String;)V
		invokevirtual java/util/ArrayList/add(Ljava/lang/Object;)V
		dup
		new java/lang/Integer
		dup
		iconst_0
		invokespecial java/lang/Integer/<init>(I)V
		invokevirtual java/util/ArrayList/add(Ljava/lang/Object;)V
		invokespecial List/<init>(Ljava/util/ArrayList;)V
		invokevirtual java/util/ArrayList/add(Ljava/lang/Object;)V
		dup
		new List
		dup 
		new java/util/ArrayList
		dup 
		invokespecial java/util/ArrayList/<init>()V
		dup
		new java/lang/String
		dup
		ldc ""
		invokespecial java/lang/String/<init>(Ljava/lang/String;)V
		invokevirtual java/util/ArrayList/add(Ljava/lang/Object;)V
		dup
		new java/lang/Integer
		dup
		iconst_0
		invokespecial java/lang/Integer/<init>(I)V
		invokevirtual java/util/ArrayList/add(Ljava/lang/Object;)V
		invokespecial List/<init>(Ljava/util/ArrayList;)V
		invokevirtual java/util/ArrayList/add(Ljava/lang/Object;)V
		dup
		new List
		dup 
		new java/util/ArrayList
		dup 
		invokespecial java/util/ArrayList/<init>()V
		dup
		new java/lang/String
		dup
		ldc ""
		invokespecial java/lang/String/<init>(Ljava/lang/String;)V
		invokevirtual java/util/ArrayList/add(Ljava/lang/Object;)V
		dup
		new java/lang/Integer
		dup
		iconst_0
		invokespecial java/lang/Integer/<init>(I)V
		invokevirtual java/util/ArrayList/add(Ljava/lang/Object;)V
		invokespecial List/<init>(Ljava/util/ArrayList;)V
		invokevirtual java/util/ArrayList/add(Ljava/lang/Object;)V
		dup
		new List
		dup 
		new java/util/ArrayList
		dup 
		invokespecial java/util/ArrayList/<init>()V
		dup
		new java/lang/String
		dup
		ldc ""
		invokespecial java/lang/String/<init>(Ljava/lang/String;)V
		invokevirtual java/util/ArrayList/add(Ljava/lang/Object;)V
		dup
		new java/lang/Integer
		dup
		iconst_0
		invokespecial java/lang/Integer/<init>(I)V
		invokevirtual java/util/ArrayList/add(Ljava/lang/Object;)V
		invokespecial List/<init>(Ljava/util/ArrayList;)V
		invokevirtual java/util/ArrayList/add(Ljava/lang/Object;)V
		dup
		new List
		dup 
		new java/util/ArrayList
		dup 
		invokespecial java/util/ArrayList/<init>()V
		dup
		new java/lang/String
		dup
		ldc ""
		invokespecial java/lang/String/<init>(Ljava/lang/String;)V
		invokevirtual java/util/ArrayList/add(Ljava/lang/Object;)V
		dup
		new java/lang/Integer
		dup
		iconst_0
		invokespecial java/lang/Integer/<init>(I)V
		invokevirtual java/util/ArrayList/add(Ljava/lang/Object;)V
		invokespecial List/<init>(Ljava/util/ArrayList;)V
		invokevirtual java/util/ArrayList/add(Ljava/lang/Object;)V
		dup
		new List
		dup 
		new java/util/ArrayList
		dup 
		invokespecial java/util/ArrayList/<init>()V
		dup
		new java/lang/String
		dup
		ldc ""
		invokespecial java/lang/String/<init>(Ljava/lang/String;)V
		invokevirtual java/util/ArrayList/add(Ljava/lang/Object;)V
		dup
		new java/lang/Integer
		dup
		iconst_0
		invokespecial java/lang/Integer/<init>(I)V
		invokevirtual java/util/ArrayList/add(Ljava/lang/Object;)V
		invokespecial List/<init>(Ljava/util/ArrayList;)V
		invokevirtual java/util/ArrayList/add(Ljava/lang/Object;)V
		dup
		new List
		dup 
		new java/util/ArrayList
		dup 
		invokespecial java/util/ArrayList/<init>()V
		dup
		new java/lang/String
		dup
		ldc ""
		invokespecial java/lang/String/<init>(Ljava/lang/String;)V
		invokevirtual java/util/ArrayList/add(Ljava/lang/Object;)V
		dup
		new java/lang/Integer
		dup
		iconst_0
		invokespecial java/lang/Integer/<init>(I)V
		invokevirtual java/util/ArrayList/add(Ljava/lang/Object;)V
		invokespecial List/<init>(Ljava/util/ArrayList;)V
		invokevirtual java/util/ArrayList/add(Ljava/lang/Object;)V
		dup
		new List
		dup 
		new java/util/ArrayList
		dup 
		invokespecial java/util/ArrayList/<init>()V
		dup
		new java/lang/String
		dup
		ldc ""
		invokespecial java/lang/String/<init>(Ljava/lang/String;)V
		invokevirtual java/util/ArrayList/add(Ljava/lang/Object;)V
		dup
		new java/lang/Integer
		dup
		iconst_0
		invokespecial java/lang/Integer/<init>(I)V
		invokevirtual java/util/ArrayList/add(Ljava/lang/Object;)V
		invokespecial List/<init>(Ljava/util/ArrayList;)V
		invokevirtual java/util/ArrayList/add(Ljava/lang/Object;)V
		dup
		new List
		dup 
		new java/util/ArrayList
		dup 
		invokespecial java/util/ArrayList/<init>()V
		dup
		new java/lang/String
		dup
		ldc ""
		invokespecial java/lang/String/<init>(Ljava/lang/String;)V
		invokevirtual java/util/ArrayList/add(Ljava/lang/Object;)V
		dup
		new java/lang/Integer
		dup
		iconst_0
		invokespecial java/lang/Integer/<init>(I)V
		invokevirtual java/util/ArrayList/add(Ljava/lang/Object;)V
		invokespecial List/<init>(Ljava/util/ArrayList;)V
		invokevirtual java/util/ArrayList/add(Ljava/lang/Object;)V
		dup
		new List
		dup 
		new java/util/ArrayList
		dup 
		invokespecial java/util/ArrayList/<init>()V
		dup
		new java/lang/String
		dup
		ldc ""
		invokespecial java/lang/String/<init>(Ljava/lang/String;)V
		invokevirtual java/util/ArrayList/add(Ljava/lang/Object;)V
		dup
		new java/lang/Integer
		dup
		iconst_0
		invokespecial java/lang/Integer/<init>(I)V
		invokevirtual java/util/ArrayList/add(Ljava/lang/Object;)V
		invokespecial List/<init>(Ljava/util/ArrayList;)V
		invokevirtual java/util/ArrayList/add(Ljava/lang/Object;)V
		dup
		new List
		dup 
		new java/util/ArrayList
		dup 
		invokespecial java/util/ArrayList/<init>()V
		dup
		new java/lang/String
		dup
		ldc ""
		invokespecial java/lang/String/<init>(Ljava/lang/String;)V
		invokevirtual java/util/ArrayList/add(Ljava/lang/Object;)V
		dup
		new java/lang/Integer
		dup
		iconst_0
		invokespecial java/lang/Integer/<init>(I)V
		invokevirtual java/util/ArrayList/add(Ljava/lang/Object;)V
		invokespecial List/<init>(Ljava/util/ArrayList;)V
		invokevirtual java/util/ArrayList/add(Ljava/lang/Object;)V
		dup
		new List
		dup 
		new java/util/ArrayList
		dup 
		invokespecial java/util/ArrayList/<init>()V
		dup
		new java/lang/String
		dup
		ldc ""
		invokespecial java/lang/String/<init>(Ljava/lang/String;)V
		invokevirtual java/util/ArrayList/add(Ljava/lang/Object;)V
		dup
		new java/lang/Integer
		dup
		iconst_0
		invokespecial java/lang/Integer/<init>(I)V
		invokevirtual java/util/ArrayList/add(Ljava/lang/Object;)V
		invokespecial List/<init>(Ljava/util/ArrayList;)V
		invokevirtual java/util/ArrayList/add(Ljava/lang/Object;)V
		dup
		new List
		dup 
		new java/util/ArrayList
		dup 
		invokespecial java/util/ArrayList/<init>()V
		dup
		new java/lang/String
		dup
		ldc ""
		invokespecial java/lang/String/<init>(Ljava/lang/String;)V
		invokevirtual java/util/ArrayList/add(Ljava/lang/Object;)V
		dup
		new java/lang/Integer
		dup
		iconst_0
		invokespecial java/lang/Integer/<init>(I)V
		invokevirtual java/util/ArrayList/add(Ljava/lang/Object;)V
		invokespecial List/<init>(Ljava/util/ArrayList;)V
		invokevirtual java/util/ArrayList/add(Ljava/lang/Object;)V
		dup
		new List
		dup 
		new java/util/ArrayList
		dup 
		invokespecial java/util/ArrayList/<init>()V
		dup
		new java/lang/String
		dup
		ldc ""
		invokespecial java/lang/String/<init>(Ljava/lang/String;)V
		invokevirtual java/util/ArrayList/add(Ljava/lang/Object;)V
		dup
		new java/lang/Integer
		dup
		iconst_0
		invokespecial java/lang/Integer/<init>(I)V
		invokevirtual java/util/ArrayList/add(Ljava/lang/Object;)V
		invokespecial List/<init>(Ljava/util/ArrayList;)V
		invokevirtual java/util/ArrayList/add(Ljava/lang/Object;)V
		dup
		new List
		dup 
		new java/util/ArrayList
		dup 
		invokespecial java/util/ArrayList/<init>()V
		dup
		new java/lang/String
		dup
		ldc ""
		invokespecial java/lang/String/<init>(Ljava/lang/String;)V
		invokevirtual java/util/ArrayList/add(Ljava/lang/Object;)V
		dup
		new java/lang/Integer
		dup
		iconst_0
		invokespecial java/lang/Integer/<init>(I)V
		invokevirtual java/util/ArrayList/add(Ljava/lang/Object;)V
		invokespecial List/<init>(Ljava/util/ArrayList;)V
		invokevirtual java/util/ArrayList/add(Ljava/lang/Object;)V
		dup
		new List
		dup 
		new java/util/ArrayList
		dup 
		invokespecial java/util/ArrayList/<init>()V
		dup
		new java/lang/String
		dup
		ldc ""
		invokespecial java/lang/String/<init>(Ljava/lang/String;)V
		invokevirtual java/util/ArrayList/add(Ljava/lang/Object;)V
		dup
		new java/lang/Integer
		dup
		iconst_0
		invokespecial java/lang/Integer/<init>(I)V
		invokevirtual java/util/ArrayList/add(Ljava/lang/Object;)V
		invokespecial List/<init>(Ljava/util/ArrayList;)V
		invokevirtual java/util/ArrayList/add(Ljava/lang/Object;)V
		dup
		new List
		dup 
		new java/util/ArrayList
		dup 
		invokespecial java/util/ArrayList/<init>()V
		dup
		new java/lang/String
		dup
		ldc ""
		invokespecial java/lang/String/<init>(Ljava/lang/String;)V
		invokevirtual java/util/ArrayList/add(Ljava/lang/Object;)V
		dup
		new java/lang/Integer
		dup
		iconst_0
		invokespecial java/lang/Integer/<init>(I)V
		invokevirtual java/util/ArrayList/add(Ljava/lang/Object;)V
		invokespecial List/<init>(Ljava/util/ArrayList;)V
		invokevirtual java/util/ArrayList/add(Ljava/lang/Object;)V
		dup
		new List
		dup 
		new java/util/ArrayList
		dup 
		invokespecial java/util/ArrayList/<init>()V
		dup
		new java/lang/String
		dup
		ldc ""
		invokespecial java/lang/String/<init>(Ljava/lang/String;)V
		invokevirtual java/util/ArrayList/add(Ljava/lang/Object;)V
		dup
		new java/lang/Integer
		dup
		iconst_0
		invokespecial java/lang/Integer/<init>(I)V
		invokevirtual java/util/ArrayList/add(Ljava/lang/Object;)V
		invokespecial List/<init>(Ljava/util/ArrayList;)V
		invokevirtual java/util/ArrayList/add(Ljava/lang/Object;)V
		dup
		new List
		dup 
		new java/util/ArrayList
		dup 
		invokespecial java/util/ArrayList/<init>()V
		dup
		new java/lang/String
		dup
		ldc ""
		invokespecial java/lang/String/<init>(Ljava/lang/String;)V
		invokevirtual java/util/ArrayList/add(Ljava/lang/Object;)V
		dup
		new java/lang/Integer
		dup
		iconst_0
		invokespecial java/lang/Integer/<init>(I)V
		invokevirtual java/util/ArrayList/add(Ljava/lang/Object;)V
		invokespecial List/<init>(Ljava/util/ArrayList;)V
		invokevirtual java/util/ArrayList/add(Ljava/lang/Object;)V
		dup
		new List
		dup 
		new java/util/ArrayList
		dup 
		invokespecial java/util/ArrayList/<init>()V
		dup
		new java/lang/String
		dup
		ldc ""
		invokespecial java/lang/String/<init>(Ljava/lang/String;)V
		invokevirtual java/util/ArrayList/add(Ljava/lang/Object;)V
		dup
		new java/lang/Integer
		dup
		iconst_0
		invokespecial java/lang/Integer/<init>(I)V
		invokevirtual java/util/ArrayList/add(Ljava/lang/Object;)V
		invokespecial List/<init>(Ljava/util/ArrayList;)V
		invokevirtual java/util/ArrayList/add(Ljava/lang/Object;)V
		dup
		new List
		dup 
		new java/util/ArrayList
		dup 
		invokespecial java/util/ArrayList/<init>()V
		dup
		new java/lang/String
		dup
		ldc ""
		invokespecial java/lang/String/<init>(Ljava/lang/String;)V
		invokevirtual java/util/ArrayList/add(Ljava/lang/Object;)V
		dup
		new java/lang/Integer
		dup
		iconst_0
		invokespecial java/lang/Integer/<init>(I)V
		invokevirtual java/util/ArrayList/add(Ljava/lang/Object;)V
		invokespecial List/<init>(Ljava/util/ArrayList;)V
		invokevirtual java/util/ArrayList/add(Ljava/lang/Object;)V
		invokespecial List/<init>(Ljava/util/ArrayList;)V
		astore 5
		new java/lang/Integer
		dup
		iconst_0
		invokespecial java/lang/Integer/<init>(I)V
		astore 6
		iconst_0
		pop
		new List
		dup
		new java/util/ArrayList
		dup
		new java/lang/Integer
		dup
		invokespecial java/lang/Integer/<init>(I)V
		invokespecial java/util/ArrayList/<init>()V
		invokespecial List/<init>(Ljava/util/ArrayList;)V
		areturn
.end method
		
.method reduce(LList;LFptr;)Ljava/lang/Integer;
		.limit stack 128
		.limit locals 128
		new java/lang/String
		dup
		ldc ""
		invokespecial java/lang/String/<init>(Ljava/lang/String;)V
		astore_3
		new java/lang/Integer
		dup
		iconst_0
		invokespecial java/lang/Integer/<init>(I)V
		astore_4
		new java/lang/Integer
		dup
		iconst_0
		invokespecial java/lang/Integer/<init>(I)V
		astore 5
		iconst_0
		pop
		iconst_0
		pop
